RS_z27
