Metadata-Version: 2.1
Name: RS-z27
Version: 0.2
Summary: Recommend System
Home-page: UNKNOWN
Author-email: sergeyroot77@gmail.com
License: UNKNOWN
Platform: UNKNOWN
